mcp_sse/__init__.py
mcp_sse/__main__.py
mcp_sse/server.py
hadron_mcp_sse-0.1.2.dist-info/METADATA
hadron_mcp_sse-0.1.2.dist-info/WHEEL
hadron_mcp_sse-0.1.2.dist-info/entry_points.txt
hadron_mcp_sse-0.1.2.dist-info/top_level.txt
hadron_mcp_sse-0.1.2.dist-info/RECORD
